revolve2/modular_robot_simulation/__init__.py
revolve2/modular_robot_simulation/_build_multi_body_systems/__init__.py
revolve2/modular_robot_simulation/_build_multi_body_systems/_body_to_multi_body_system_converter.py
revolve2/modular_robot_simulation/_build_multi_body_systems/_body_to_multi_body_system_mapping.py
revolve2/modular_robot_simulation/_build_multi_body_systems/_builders/__init__.py
revolve2/modular_robot_simulation/_build_multi_body_systems/_builders/_active_hinge_builder.py
revolve2/modular_robot_simulation/_build_multi_body_systems/_builders/_active_hinge_sensor_builder.py
revolve2/modular_robot_simulation/_build_multi_body_systems/_builders/_attachment_face_builder.py
revolve2/modular_robot_simulation/_build_multi_body_systems/_builders/_brick_builder.py
revolve2/modular_robot_simulation/_build_multi_body_systems/_builders/_builder.py
revolve2/modular_robot_simulation/_build_multi_body_systems/_builders/_camera_sensor_builder.py
revolve2/modular_robot_simulation/_build_multi_body_systems/_builders/_core_builder.py
revolve2/modular_robot_simulation/_build_multi_body_systems/_builders/_imu_sensor_builder.py
revolve2/modular_robot_simulation/_build_multi_body_systems/_convert_color.py
revolve2/modular_robot_simulation/_build_multi_body_systems/_get_builder.py
revolve2/modular_robot_simulation/_build_multi_body_systems/_unbuilt_child.py
revolve2/modular_robot_simulation/_convert_terrain.py
revolve2/modular_robot_simulation/_modular_robot_control_interface_impl.py
revolve2/modular_robot_simulation/_modular_robot_scene.py
revolve2/modular_robot_simulation/_modular_robot_simulation_handler.py
revolve2/modular_robot_simulation/_modular_robot_simulation_state.py
revolve2/modular_robot_simulation/_scene_simulation_state.py
revolve2/modular_robot_simulation/_sensor_state_impl/__init__.py
revolve2/modular_robot_simulation/_sensor_state_impl/_active_hinge_sensor_state_impl.py
revolve2/modular_robot_simulation/_sensor_state_impl/_camera_sensor_state_impl.py
revolve2_modular_robot_simulation-1.2.4.dist-info/METADATA
revolve2_modular_robot_simulation-1.2.4.dist-info/WHEEL
revolve2_modular_robot_simulation-1.2.4.dist-info/RECORD
