Metadata-Version: 2.3
Name: revolve2-modular-robot-simulation
Version: 1.2.4
Summary: Revolve2: Functionality to define scenes with modular robots in a terrain and simulate them.
Author: Aart Stuurman
Author-email: aartstuurman@hotmail.com
Requires-Python: >=3.10,<3.12
Classifier: Development Status :: 5 - Production/Stable
Classifier: Intended Audience :: Science/Research
Classifier: License :: OSI Approved :: GNU Lesser General Public License v3 (LGPLv3)
Classifier: Operating System :: OS Independent
Classifier: Programming Language :: Python :: 3
Classifier: Programming Language :: Python :: 3.10
Classifier: Programming Language :: Python :: 3.11
Classifier: Topic :: Scientific/Engineering
Classifier: Typing :: Typed
Provides-Extra: dev
Requires-Dist: revolve2-modular-robot (==1.2.4)
Requires-Dist: revolve2-simulation (==1.2.4)
Project-URL: Repository, https://github.com/ci-group/revolve2
